bosa_connectors/__init__.py
gl_connectors_sdk/__init__.py
gl_connectors_sdk/action.py
gl_connectors_sdk/action_response.py
gl_connectors_sdk/connector.py
gl_connectors_sdk/constant.py
gl_connectors_sdk/module.py
gl_connectors_sdk/tool.py
gl_connectors_sdk/auth/__init__.py
gl_connectors_sdk/auth/api_key.py
gl_connectors_sdk/auth/base.py
gl_connectors_sdk/helpers/__init__.py
gl_connectors_sdk/helpers/authenticator.py
gl_connectors_sdk/helpers/integrations.py
gl_connectors_sdk/helpers/tool_builder/__init__.py
gl_connectors_sdk/helpers/tool_builder/base.py
gl_connectors_sdk/helpers/tool_builder/gllm.py
gl_connectors_sdk/helpers/tool_builder/json_schema_generator.py
gl_connectors_sdk/helpers/tool_builder/langchain.py
gl_connectors_sdk/models/__init__.py
gl_connectors_sdk/models/action.py
gl_connectors_sdk/models/file.py
gl_connectors_sdk/models/result.py
gl_connectors_sdk/models/token.py
gl_connectors_sdk/models/user.py
gl_connectors_sdk-0.1.0.dist-info/METADATA
gl_connectors_sdk-0.1.0.dist-info/WHEEL
gl_connectors_sdk-0.1.0.dist-info/RECORD
